README.rst
setup.cfg
setup.py
autopython/__init__.py
autopython/console.py
autopython/core.py
autopython/script_parser.py
autopython.egg-info/PKG-INFO
autopython.egg-info/SOURCES.txt
autopython.egg-info/dependency_links.txt
autopython.egg-info/requires.txt
autopython.egg-info/top_level.txt
bin/autopython