Metadata-Version: 1.1
Name: autopython
Version: 0.3
Summary: Autoscripting for Python 3
Home-page: https://github.com/gosella/autopython
Author: Germán Osella Massa
Author-email: german.osella@nexo.unnoba.edu.ar
License: GPLv3
Download-URL: https://github.com/gosella/autopython
Keywords: python3,presentation,autoscripting
Platform: UNKNOWN
